[
    {
        "recipe": "How to Fry Pork Belly (Lechon Kawali)",
        "url": "https://panlasangpinoy.com/cooking-lechon-kawali-fried-pork-filipino-recipe/"
    },
    {
        "recipe": "Kinamatisang Baboy",
        "url": "https://panlasangpinoy.com/kinamatisang-baboy/"
    },
    {
        "recipe": "Sotanghon Overload",
        "url": "https://panlasangpinoy.com/sotanghon-overload/"
    },
    {
        "recipe": "Batchoy Tagalog",
        "url": "https://panlasangpinoy.com/batchoy-tagalog/"
    },
    {
        "recipe": "Paksiw Na Baboy",
        "url": "https://panlasangpinoy.com/paksiw-na-baboy/"
    },
    {
        "recipe": "Special Chicken Afritada",
        "url": "https://panlasangpinoy.com/special-chicken-afritada/"
    },
    {
        "recipe": "Sotanghon And Egg Noodle Soup",
        "url": "https://panlasangpinoy.com/sotanghon-and-egg-noodle-soup/"
    },
    {
        "recipe": "No Grill Pork Ribs Barbecue",
        "url": "https://panlasangpinoy.com/no-grill-pork-ribs-barbecue/"
    },
    {
        "recipe": "Beef Chop Suey",
        "url": "https://panlasangpinoy.com/beef-chop-suey/"
    },
    {
        "recipe": "Mie Goreng",
        "url": "https://panlasangpinoy.com/mie-goreng/"
    },
    {
        "recipe": "Batangas Kaldereta",
        "url": "https://panlasangpinoy.com/batangas-kaldereta/"
    },
    {
        "recipe": "Burger Steak Sardinas",
        "url": "https://panlasangpinoy.com/burger-steak-sardinas/"
    },
    {
        "recipe": "Kung Pao Chicken Recipe",
        "url": "https://panlasangpinoy.com/kung-pao-chicken-recipe/"
    },
    {
        "recipe": "Crispy Garlic Fried Chicken Wings",
        "url": "https://panlasangpinoy.com/crispy-garlic-fried-chicken-wings/"
    },
    {
        "recipe": "Sarciadong Pechay",
        "url": "https://panlasangpinoy.com/sarciadong-pechay/"
    },
    {
        "recipe": "What is patola (loofah)?",
        "url": "https://panlasangpinoy.com/what-is-patola-loofah/"
    },
    {
        "recipe": "Calderetang Manok",
        "url": "https://panlasangpinoy.com/calderetang-manok/"
    },
    {
        "recipe": "Ginisang Repolyo with Egg",
        "url": "https://panlasangpinoy.com/ginisang-repolyo-with-egg/"
    },
    {
        "recipe": "Chicken Gizzard Ginataan",
        "url": "https://panlasangpinoy.com/chicken-gizzard-ginataan/"
    },
    {
        "recipe": "Filipino Chicken Adobo Recipe",
        "url": "https://panlasangpinoy.com/filipino-chicken-adobo-recipe/"
    },
    {
        "recipe": "Pork Kilawin",
        "url": "https://panlasangpinoy.com/pork-kilawin/"
    },
    {
        "recipe": "Pork Hamonado Recipe",
        "url": "https://panlasangpinoy.com/pork-hamonado/"
    },
    {
        "recipe": "Braised Pork Belly with Potato and Peppers",
        "url": "https://panlasangpinoy.com/braised-pork-belly-with-potato-and-peppers/"
    },
    {
        "recipe": "Fried Eggplant (Crispy Fritters)",
        "url": "https://panlasangpinoy.com/fried-eggplant-crispy-fritters/"
    }
]